django_wedsite-0.0.11.dist-info/DESCRIPTION.rst
django_wedsite-0.0.11.dist-info/METADATA
django_wedsite-0.0.11.dist-info/RECORD
django_wedsite-0.0.11.dist-info/WHEEL
django_wedsite-0.0.11.dist-info/metadata.json
django_wedsite-0.0.11.dist-info/top_level.txt
wedsite/__init__.py
wedsite/admin.py
wedsite/apps.py
wedsite/backends.py
wedsite/conf.py
wedsite/context_processors.py
wedsite/forms.py
wedsite/geocode.py
wedsite/models.py
wedsite/settings.py
wedsite/tests.py
wedsite/urls.py
wedsite/views.py
wedsite/management/__init__.py
wedsite/management/commands/__init__.py
wedsite/management/commands/email.py
wedsite/management/commands/loadguestlist.py
wedsite/migrations/0001_initial.py
wedsite/migrations/0002_rsvp_comment.py
wedsite/migrations/0003_rsvp_blank_comment.py
wedsite/migrations/__init__.py
wedsite/static/.DS_Store
wedsite/static/css/email.css
wedsite/static/css/style.css
wedsite/static/images/amazon_registry.png
wedsite/static/images/main_jumbotron.jpg
wedsite/static/images/favicons/favicon-heart.ico
wedsite/static/images/team_photos/team_member.jpg
wedsite/templates/email/email.html
wedsite/templates/email/email.txt
wedsite/templates/registration/create_user.html
wedsite/templates/registration/logged_out.html
wedsite/templates/registration/login.html
wedsite/templates/registration/password_reset_complete.html
wedsite/templates/registration/password_reset_confirm.html
wedsite/templates/registration/password_reset_done.html
wedsite/templates/registration/password_reset_form.html
wedsite/templates/wedding/blocks/base.html
wedsite/templates/wedding/blocks/explore_map.html
wedsite/templates/wedding/blocks/responsive_map.html
wedsite/templates/wedding/pages/contact.html
wedsite/templates/wedding/pages/events.html
wedsite/templates/wedding/pages/explore.html
wedsite/templates/wedding/pages/gifts.html
wedsite/templates/wedding/pages/index.html
wedsite/templates/wedding/pages/rsvp.html
wedsite/templates/wedding/pages/story.html
wedsite/templates/wedding/pages/team.html
wedsite/templates/wedding/pages/traditions.html
wedsite/templates/wedding/pages/travel.html
wedsite/templates/wedding/pages/wedding.html
