Metadata-Version: 2.0
Name: django-wedsite
Version: 0.0.11
Summary: A simple open-source django wedding website
Home-page: https://www.wedsite.io/
Author: Dan Pipe-Mazo
Author-email: dpipemazo@gmail.com
License: GPLv3
Platform: UNKNOWN
Classifier: License :: OSI Approved :: GNU General Public License v3 (GPLv3)
Classifier: Environment :: Web Environment
Classifier: Framework :: Django
Classifier: Framework :: Django :: 1.11
Classifier: Intended Audience :: Developers
Classifier: Operating System :: OS Independent
Classifier: Programming Language :: Python
Classifier: Programming Language :: Python :: 3 :: Only 
Classifier: Topic :: Internet :: WWW/HTTP
Classifier: Topic :: Internet :: WWW/HTTP :: Dynamic Content
Requires-Dist: dj-database-url (==0.4.1)
Requires-Dist: Django (==1.11)
Requires-Dist: gunicorn (==19.6.0)
Requires-Dist: psycopg2 (==2.7.3)
Requires-Dist: whitenoise (==3.3.0)
Requires-Dist: requests (==2.9.1)
Requires-Dist: django-easy-maps (==0.9.3)
Requires-Dist: raven (>=3)
Requires-Dist: django-tz-detect (==0.2.8)
Requires-Dist: django-inlinecss (==0.1.2)
Requires-Dist: lorem
Requires-Dist: django-appconf
